subclass/__init__.py
subclass/core/__init__.py
subclass/tests/__init__.py
subclass/tests/test_core.py
subclass-0.1.2.dist-info/LICENSE.txt
subclass-0.1.2.dist-info/METADATA
subclass-0.1.2.dist-info/WHEEL
subclass-0.1.2.dist-info/top_level.txt
subclass-0.1.2.dist-info/RECORD
