Metadata-Version: 2.1
Name: subclass
Version: 0.1.2
Summary: subclass
Author-email: Johannes <johannes-programming@mailfence.com>
License: The MIT License (MIT)
Project-URL: Documentation, https://pypi.org/project/subclass
Project-URL: Download, https://pypi.org/project/subclass/#files
Project-URL: Source, https://github.com/johannes-programming/subclass
Classifier: Development Status :: 3 - Alpha
Classifier: License :: OSI Approved :: MIT License
Classifier: Programming Language :: Python
Classifier: Programming Language :: Python :: 3
Classifier: Programming Language :: Python :: 3 :: Only
Requires-Python: >=3.8
License-File: LICENSE.txt
